README.txt
setup.py
assignment/_init_.py
assignment/azbook_scrape.py
assignment/main.py
assignment/sastobook_scrape.py
assignment.egg-info/PKG-INFO
assignment.egg-info/SOURCES.txt
assignment.egg-info/dependency_links.txt
assignment.egg-info/requires.txt
assignment.egg-info/top_level.txt