Metadata-Version: 1.0
Name: assignment
Version: 0.3
Summary: calculation of minimum price of given book
Home-page: https://github.com/ptyma/MinimumPriceBookScraper
Author: Pratima Chettri
Author-email: chettripratima@gmail.com
License: UNKNOWN
Platform: UNKNOWN
